examples/arxiv_scraping.py
examples/scrape_master_app.py
examples/youtube_scraping.py
scrapemaster/__init__.py
scrapemaster/core.py
scrapemaster/exceptions.py
scrapemaster/utils.py
scrapemaster-0.6.0.dist-info/licenses/LICENSE
tests/test_core.py
tests/test_utils.py
scrapemaster-0.6.0.dist-info/METADATA
scrapemaster-0.6.0.dist-info/WHEEL
scrapemaster-0.6.0.dist-info/top_level.txt
scrapemaster-0.6.0.dist-info/RECORD
