Metadata-Version: 2.4
Name: scrapemaster
Version: 0.6.0
Summary: A versatile web scraping library with configurable multi-strategy fetching and specialized handlers
Author-email: ParisNeo <parisneo_ai@gmail.com>
License-Expression: Apache-2.0
Project-URL: Homepage, https://github.com/ParisNeo/ScrapeMaster
Project-URL: Issues, https://github.com/ParisNeo/ScrapeMaster/issues
Classifier: Development Status :: 4 - Beta
Classifier: Intended Audience :: Developers
Classifier: Operating System :: OS Independent
Classifier: Programming Language :: Python :: 3
Classifier: Programming Language :: Python :: 3.9
Classifier: Programming Language :: Python :: 3.10
Classifier: Programming Language :: Python :: 3.11
Classifier: Programming Language :: Python :: 3.12
Classifier: Topic :: Internet :: WWW/HTTP
Classifier: Topic :: Software Development :: Libraries :: Python Modules
Classifier: Topic :: Text Processing :: Markup :: HTML
Requires-Python: >=3.9
License-File: LICENSE
Requires-Dist: requests>=2.25.1
Requires-Dist: beautifulsoup4>=4.9.3
Requires-Dist: lxml>=4.6.3
Requires-Dist: selenium>=4.10.0
Requires-Dist: webdriver-manager>=4.0.0
Requires-Dist: undetected-chromedriver>=3.1.5
Requires-Dist: markdownify>=0.11.6
Requires-Dist: pipmaster>=0.7.0
Requires-Dist: ascii_colors>=0.10.0
Requires-Dist: youtube-transcript-api>=0.6.0
Requires-Dist: wikipedia>=1.4.0
Requires-Dist: docling>=1.0.0
Provides-Extra: dev
Requires-Dist: pytest>=6.2.4; extra == "dev"
Requires-Dist: flake8>=3.9.2; extra == "dev"
Requires-Dist: black>=22.3.0; extra == "dev"
Requires-Dist: pytest-mock>=3.6.1; extra == "dev"
Dynamic: license-file
